LICENSE.txt
README.md
pyproject.toml
setup.cfg
setup.py
sanic_camelcase_middleware/__init__.py
sanic_camelcase_middleware.egg-info/PKG-INFO
sanic_camelcase_middleware.egg-info/SOURCES.txt
sanic_camelcase_middleware.egg-info/dependency_links.txt
sanic_camelcase_middleware.egg-info/not-zip-safe
sanic_camelcase_middleware.egg-info/requires.txt
sanic_camelcase_middleware.egg-info/top_level.txt