Metadata-Version: 2.1
Name: sanic-camelcase-middleware
Version: 1.3.1
Summary: Middleware for camelizing request and response bodies for Sanic
Home-page: https://nf1s.github.io/sanic-camelcase-middleware/
Author: Ahmed Nafies
Author-email: ahmed.nafies@gmail.com
License: MIT
Project-URL: Documentation, https://nf1s.github.io/sanic-camelcase-middleware/
Project-URL: Source, https://github.com/nf1s/sanic-camelcase-middleware
Platform: UNKNOWN
Classifier: Intended Audience :: Developers
Classifier: Topic :: Software Development :: Build Tools
Classifier: License :: OSI Approved :: MIT License
Classifier: Programming Language :: Python :: 3
Classifier: Programming Language :: Python :: 3.7
Classifier: Programming Language :: Python :: 3.8
Requires-Python: >=3.7
License-File: LICENSE.txt
